src/__init__.py
src/alma_data_processing/__init__.py
src/alma_data_processing/alma_data_processing.py
src/external_libs/__init__.py
src/external_libs/salat.py
test/__init__.py
test/alma_data_processing/__init__.py
test/alma_data_processing/test_alma_processor_tests.py
AlmaTracking-0.1.0.dist-info/METADATA
AlmaTracking-0.1.0.dist-info/WHEEL
AlmaTracking-0.1.0.dist-info/top_level.txt
AlmaTracking-0.1.0.dist-info/RECORD
