Metadata-Version: 2.1
Name: AlmaTracking
Version: 0.1.0
Summary: A dynamic repository for streamlined Alma tracking.
Home-page: https://github.com/JavierOrdonezA/ALMA-Cold-Region-Tracker-Dynamic-Event-Detection-and-Analysis
Author: F. Javier Ordonez - Araujo
Author-email: fordonezaraujo@gmail.com
Classifier: Programming Language :: Python :: 3
Classifier: License :: OSI Approved :: MIT License
Classifier: Operating System :: OS Independent
Requires-Python: >=3.6
Requires-Dist: astropy ~=5.1
Requires-Dist: radio-beam ~=0.3.3
Requires-Dist: schwifty ~=2023.6.0
Requires-Dist: numpy ~=1.22
Requires-Dist: scipy ~=1.8
Requires-Dist: scikit-image ~=0.20
Requires-Dist: matplotlib ~=3.5
Requires-Dist: matplotlib-inline ~=0.1
Requires-Dist: seaborn ~=0.12
Requires-Dist: numpydoc ~=1.5
Requires-Dist: tqdm ~=4.64
Requires-Dist: numpy ~=1.22.4
Requires-Dist: scikit-image ~=0.20.0
Requires-Dist: astropy ~=5.3.4
Requires-Dist: scipy ~=1.10.1
Requires-Dist: radio-beam ~=0.3.7
